{
  "id": "dracula",
  "name": "Dracula",
  "author": "Zeno Rocha",
  "type": "dark",
  "colors": {
    "bg": "#282a36",
    "bg-card": "#21222c",
    "bg-surface": "#343746",
    "bg-elevated": "#44475a",
    "border": "#44475a",
    "border-dim": "#343746",
    "text-primary": "#f8f8f2",
    "text-secondary": "#e2e2dc",
    "text-muted": "#6272a4",
    "text-dim": "#545d82",
    "text-faint": "#44475a",
    "text-ghost": "#383a4a",
    "accent": "#50fa7b",
    "accent-bg": "#1e3a28",
    "accent-border": "rgba(80, 250, 123, 0.25)",
    "accent-foreground": "#282a36",
    "danger": "#ff5555",
    "danger-bg": "#3a1e22",
    "danger-border": "rgba(255, 85, 85, 0.25)",
    "warn": "#f1fa8c",
    "warn-bg": "#3a3a1e",
    "warn-border": "rgba(241, 250, 140, 0.25)",
    "info": "#8be9fd",
    "info-bg": "#1e2e36",
    "info-border": "rgba(139, 233, 253, 0.25)",
    "background": "#282a36",
    "foreground": "#f8f8f2",
    "card": "#21222c",
    "card-foreground": "#f8f8f2",
    "popover": "#21222c",
    "popover-foreground": "#f8f8f2",
    "primary": "#bd93f9",
    "primary-foreground": "#282a36",
    "secondary": "#343746",
    "secondary-foreground": "#f8f8f2",
    "muted": "#343746",
    "muted-foreground": "#6272a4",
    "destructive": "#ff5555",
    "input": "#44475a",
    "ring": "#bd93f9"
  }
}
