{
  "id": "rose-pine",
  "name": "Rose Pine",
  "author": "Rose Pine",
  "type": "dark",
  "colors": {
    "bg": "#191724",
    "bg-card": "#1f1d2e",
    "bg-surface": "#26233a",
    "bg-elevated": "#2a2740",
    "border": "#393552",
    "border-dim": "#26233a",
    "text-primary": "#e0def4",
    "text-secondary": "#d3d0e8",
    "text-muted": "#908caa",
    "text-dim": "#6e6a86",
    "text-faint": "#524f67",
    "text-ghost": "#393552",
    "accent": "#31748f",
    "accent-bg": "#1a2630",
    "accent-border": "rgba(49, 116, 143, 0.3)",
    "accent-foreground": "#e0def4",
    "danger": "#eb6f92",
    "danger-bg": "#2e1a28",
    "danger-border": "rgba(235, 111, 146, 0.25)",
    "warn": "#f6c177",
    "warn-bg": "#2e2618",
    "warn-border": "rgba(246, 193, 119, 0.25)",
    "info": "#9ccfd8",
    "info-bg": "#1a2a2e",
    "info-border": "rgba(156, 207, 216, 0.25)",
    "background": "#191724",
    "foreground": "#e0def4",
    "card": "#1f1d2e",
    "card-foreground": "#e0def4",
    "popover": "#1f1d2e",
    "popover-foreground": "#e0def4",
    "primary": "#c4a7e7",
    "primary-foreground": "#191724",
    "secondary": "#26233a",
    "secondary-foreground": "#e0def4",
    "muted": "#26233a",
    "muted-foreground": "#908caa",
    "destructive": "#eb6f92",
    "input": "#393552",
    "ring": "#c4a7e7"
  }
}
